vipas/__init__.py
vipas/_rest.py
vipas/challenge.py
vipas/config.py
vipas/constant.py
vipas/error_suggestions.py
vipas/exceptions.py
vipas/logger.py
vipas/model.py
vipas/user.py
vipas-1.1.2.dist-info/LICENSE
vipas-1.1.2.dist-info/METADATA
vipas-1.1.2.dist-info/WHEEL
vipas-1.1.2.dist-info/top_level.txt
vipas-1.1.2.dist-info/RECORD
