Metadata-Version: 2.2
Name: vipas
Version: 1.1.2
Summary: Python SDK for Vipas AI Platform
Home-page: https://github.com/vipas-engineering/vipas-python-sdk
Author: Vipas Team
Author-email: contact@vipas.ai
License: 
Project-URL: Homepage, https://github.com/vipas-engineering/vipas-python-sdk
Classifier: License :: OSI Approved :: Apache Software License
Classifier: Programming Language :: Python :: 3
Classifier: Programming Language :: Python :: 3.7
Classifier: Programming Language :: Python :: 3.8
Classifier: Programming Language :: Python :: 3.9
Classifier: Operating System :: OS Independent
Requires-Python: >=3.7
License-File: LICENSE
Requires-Dist: urllib3
Requires-Dist: pydantic
Requires-Dist: typing-extensions
Requires-Dist: ratelimit
Requires-Dist: pybreaker
Requires-Dist: streamlit
Requires-Dist: httpx
Dynamic: author
Dynamic: author-email
Dynamic: home-page
